{
  "clients": {
    "widget": {
      "header": "Featured News"
    },
    "link": "",
    "title": "",
    "description": [""],
    "button": {
      "style": "red",
      "link": "LINK?utm_medium=email&utm_campaign=2024-07&utm_source=insights-newsletter&utm_content=button-contact-us",
      "text": "Contact Us",
      "width": 150
    }
  },
  "jld": {
    "widget": {
      "header": "Justia Gold Placement Price Increase!"
    },
    "link": "",
    "title": "Grab a Justia Gold Placement Before the Price Goes Up!",
    "description": [
      "<strong></strong>",
      "Justia helps lawyers reach new clients with Justia Premium Placements in our Justia Lawyer Directory. Make sure you can be seen when potential clients search for a lawyer in your area. These are the final weeks to lock in 2023 prices before they go up on March 15, 2024. Lock in 2023 prices, and don't miss out on this opportunity to stand out before potential clients."
    ],
    "button": {
      "style": "justia-blue-ghost",
      "link": "https://www.justia.com/marketing/contact/lawyer-directory/",
      "text": "I Want 2023 Prices",
      "width": 170
    }
  },
  "complimentary": {
    "widget": {
      "header": "Complimentary Virtual CLE Conference"
    },
    "link": "",
    "title": "",
    "description": [""]
  }
}
