{
  "news": [
    {
      "logoName": "[alt logo name]",
      "description": "Gerry Filippatos of <strong>Phillips & Associates</strong> was quoted by Bloomberg Law regarding doctor sexual assault claims",
      "button": {
        "text": "Read More",
        "link": "https://news.bloomberglaw.com/health-law-and-business/clergy-sex-abuse-cases-supply-model-for-doctor-assault-claims"
      }
    },
    {
      "logoName": "[alt logo name]",
      "description": "Retired Justice Barry Kramer Joins <strong>McNamee Lochner P.C.</strong>",
      "button": {
        "text": "Read More",
        "link": "https://www.law.com/newyorklawjournal/2019/01/04/retired-justice-barry-kramer-joins-mcnamee-lochner/"
      }
    }
  ]
}
