{
  "places": [
    {
      "area": "Location Flexible / Remote",
      "jobs": [
        {
          "title": "Counsel, Privacy and Data Security",
          "company": "Zillow Group",
          "link": "https://zillow.wd5.myworkdayjobs.com/en-US/Zillow_Group_External/job/Counsel--Privacy-and-Data-Security_P742480-1"
        },
        {
          "title": "Manager, Counsel",
          "company": "HubSpot",
          "link": "https://www.hubspot.com/careers/jobs/5194648"
        },
        {
          "title": "Senior Counsel",
          "company": "Kickstarter",
          "link": "https://boards.greenhouse.io/kickstarter/jobs/4040056007?gh_jid=4040056007"
        },
        {
          "title": "Senior Product Counsel",
          "company": "Zoom",
          "link": "https://careers.zoom.us/jobs/senior-product-counsel-remote-united-states-c82dfeba-61cc-4aae-8cab-095e4a52180d"
        }
      ]
    },
    {
      "area": "California - Los Angeles Metro Area / Southern CA",
      "jobs": [
        {
          "title": "Associate General Counsel, Venues",
          "company": "LA Clippers",
          "link": "https://www.nba.com/clippers/company/careers/openposition?4273139006&gh_jid=4273139006"
        },
        {
          "title": "Litigation Counsel, Disneyland Resort",
          "company": "The Walt Disney Company",
          "link": "https://jobs.disneycareers.com/job/anaheim/litigation-counsel-disneyland-resort/391/55492447952"
        },
        {
          "title": "Corporate Counsel",
          "company": "Amazon",
          "link": "https://amazon.jobs/en/jobs/2459798/corporate-counsel"
        },
        {
          "title": "Counsel, Legal Affairs",
          "company": "Warner Bros. Discovery",
          "link": "https://careers.wbd.com/global/en/job/R000071468/Counsel-Legal-Affairs"
        },
        {
          "title": "Deputy City Attorney, Land Use Division",
          "company": "Los Angeles City Attorney's Office",
          "link": "https://drive.google.com/file/d/10mfoKmbvaMvUn1N3aH8hp0HyoTr5HbM5/view"
        },
        {
          "title": "Employment Counsel",
          "company": "SpaceX",
          "link": "https://boards.greenhouse.io/spacex/jobs/6925955002?gh_jid=6925955002"
        },
        {
          "title": "Senior Counsel ",
          "company": "Sweetgreen",
          "link": "https://careers.sweetgreen.com/jobs/5394743"
        },
        {
          "title": "Senior Counsel",
          "company": "TikTok",
          "link": "https://careers.tiktok.com/position/7257554223243643197/detail"
        },
        {
          "title": "Staff Attorney, Homeless Veterans Project",
          "company": "Inner City Law Center",
          "link": "https://innercitylaw.org/join-our-team/?gnk=job&gni=8a78879e882cac0b018858f0d8fb56a1&lang=en"
        }
      ]
    },
    {
      "area": "California - San Francisco Bay Area / Northern CA",
      "jobs": [
        {
          "title": "Corporate Counsel",
          "company": "Amazon",
          "link": "https://amazon.jobs/en/jobs/2459798/corporate-counsel"
        },
        {
          "title": "Commercial Counsel",
          "company": "C3 AI",
          "link": "https://c3.ai/job-description/?gh_jid=5316319002"
        },
        {
          "title": "Corporate Legal Counsel",
          "company": "Canva",
          "link": "https://www.lifeatcanva.com/en/jobs/fcdc5550-f727-4cea-8665-916572f67d5a/corporate-legal-counsel/"
        },
        {
          "title": "Head General Counsel",
          "company": "San Francisco Unified School District",
          "link": "https://careers.sfusd.edu/job/San-Francisco-Head-General-Counsel%2C-SFUSD-%289988%29-CA-94102/1024323700/"
        },
        {
          "title": "Junior Contracts Lawyer",
          "company": "Federal Reserve Bank of San Francisco",
          "link": "https://rb.wd5.myworkdayjobs.com/en-US/FRS/job/Junior-Contracts-Lawyer_R-0000019553-1"
        },
        {
          "title": "Legal Research Attorney - Criminal",
          "company": "Superior Court of California, County of Contra Costa",
          "link": "https://www.governmentjobs.com/careers/contracostacourts/jobs/4221612/legal-research-attorney-criminal"
        },
        {
          "title": "Senior Counsel, Commercial",
          "company": "DoorDash",
          "link": "https://careers.doordash.com/jobs/5416412"
        },
        {
          "title": "Senior Counsel, M&A",
          "company": "Uber",
          "link": "https://www.uber.com/global/en/careers/list/124379/"
        },
        {
          "title": "Social Security/SSI Staff Attorney - Alameda County",
          "company": "BayLegal",
          "link": "https://bayarealegalaid.applytojob.com/apply/zLgXrBp4fN/Social-SecuritySSI-Staff-Attorney-Alameda-County"
        },
        {
          "title": "Staff Attorney - Temporary",
          "company": "Bay Area Air Quality Management District",
          "link": "https://www.governmentjobs.com/careers/baaqmd/jobs/4225977/staff-attorney-temporary"
        }
      ]
    },
    {
      "area": "DC - Washington Metro Area",
      "jobs": [
        {
          "title": "Assistant General Counsel",
          "company": "Administrative Office of the U.S. Courts",
          "link": "https://www.usajobs.gov/job/751215200"
        },
        {
          "title": "Assistant General Counsel",
          "company": "World Wildlife Fund",
          "link": "https://careers-wwfus.icims.com/jobs/3579/assistant-general-counsel---24038/job"
        },
        {
          "title": "Attorney-Adviser (Counsel)",
          "company": "Federal Deposit Insurance Corporation",
          "link": "https://www.usajobs.gov/job/753255700"
        },
        {
          "title": "Attorney-Adviser",
          "company": "Securities and Exchange Commission",
          "link": "https://www.usajobs.gov/job/751476300"
        },
        {
          "title": "Attorney-Advisor",
          "company": "Millennium Challenge Corporation",
          "link": "https://mccjobs.usajobs.gov/job/754857200"
        },
        {
          "title": "Attorney Advisor (General)",
          "company": "United States Copyright Office",
          "link": "https://www.usajobs.gov/job/750477900"
        },
        {
          "title": "Attorney Advisor, Equitable Land Use Section, Commercial Division ",
          "company": "District of Columbia - Office of the Attorney General",
          "link": "https://jobs.jobvite.com/oagdc/job/otWBofw8"
        },
        {
          "title": "Associate General Counsel, International Law Practice Group",
          "company": "NASA",
          "link": "https://www.usajobs.gov/job/752851500"
        },
        {
          "title": "Corporate Counsel",
          "company": "Amazon",
          "link": "https://amazon.jobs/en/jobs/2459798/corporate-counsel"
        },
        {
          "title": "Deputy General Counsel",
          "company": "Consumer Product Safety Commission",
          "link": "https://www.usajobs.gov/job/754744000"
        },
        {
          "title": "Deputy Staff Counsel",
          "company": "District of Columbia Courts",
          "link": "https://www.usajobs.gov/job/752420300"
        },
        {
          "title": "General Attorney",
          "company": "U.S. Department of Energy",
          "link": "https://www.usajobs.gov/job/751904700"
        }
      ]
    },
    {
      "area": "Illinois - Chicago Metro Area",
      "jobs": [
        {
          "title": "Assistant Vice President, General Counsel",
          "company": "Museum of Science and Industry, Chicago",
          "link": "https://msichicago.applytojob.com/apply/oddl6cQ9dy/Assistant-Vice-President-General-Counsel"
        },
        {
          "title": "Corporate Attorney",
          "company": "RWE Clean Energy",
          "link": "https://www.rwe.com/en/rwe-careers-portal/job-offers/details/?id=83330-en_GB"
        },
        {
          "title": "General Counsel and Chief Compliance Officer",
          "company": "Chicago State University",
          "link": "https://chicagostate.peopleadmin.com/postings/14680"
        },
        {
          "title": "Senior Employment Counsel",
          "company": "Dyson",
          "link": "https://careers.dyson.com/en-gb/job-description/senior-employment-counsel/JR23419"
        },
        {
          "title": "Senior Manager - Title Operations and Legal Counsel (Illinois)",
          "company": "Title Forward (Redfin)",
          "link": "https://redfin.wd1.myworkdayjobs.com/Title_Forward/job/IL---Chicago/Senior-Manager---Title-Operations-and-Legal-Counsel--Illinois-_51373"
        },
        {
          "title": "Staff Attorney, Fair Housing Legal Clinic ",
          "company": "University of Illinois Chicago",
          "link": "https://uic.csod.com/ux/ats/careersite/1/home/requisition/6934?c=uic"
        }
      ]
    },
    {
      "area": "Massachusetts - Boston Metro Area",
      "jobs": [
        {
          "title": "Associate Counsel to the House (Office of Legal Counsel)",
          "company": "Massachusetts House of Representatives",
          "link": "https://massanf.taleo.net/careersection/ex/jobdetail.ftl?job=23000B0Y"
        },
        {
          "title": "Associate General Counsel",
          "company": "Blue Cross Blue Shield of Massachusetts",
          "link": "https://careers.bluecrossma.org/us/en/job/R06699/Associate-General-Counsel"
        },
        {
          "title": "Director of Public Interest & Government, Center for Co-op and Career Development",
          "company": "Northeastern University School of Law",
          "link": "https://northeastern.wd1.myworkdayjobs.com/en-US/careers/job/Director-of-Public-Interest-and-Government-for-the-Center-for-Co-op-and-Career-Development--School-of-Law_R119459-1"
        },
        {
          "title": "Staff Attorney, Tax Litigation Clinic",
          "company": "Harvard Law School",
          "link": "https://sjobs.brassring.com/TGnewUI/Search/home/HomeWithPreLoad?partnerid=25240&siteid=5341&PageType=JobDetails&jobid=1998108"
        },
        {
          "title": "Student Loan Advocate Attorney, Insurance & Financial Services Division",
          "company": "Attorney General's Office, Commonwealth of Massachusetts",
          "link": "https://ago-ma.iGreentree.com/CSS_External/CSSPage_Referred.ASP?Req=24-042"
        }
      ]
    },
    {
      "area": "New York - New York City Metro Area",
      "jobs": [
        {
          "title": "Assistant General Counsel",
          "company": "American Museum of Natural History",
          "link": "https://careers.amnh.org/postings/3820"
        },
        {
          "title": "Assistant General Counsel",
          "company": "MTA",
          "link": "https://careers.mta.org/jobs/13411248-assistant-general-counsel"
        },
        {
          "title": "Bill Drafting Counsel",
          "company": "New York City Council",
          "link": "https://council.nyc.gov/jobs/bill-drafting-counsel/"
        },
        {
          "title": "Corporate Attorney",
          "company": "RWE Clean Energy",
          "link": "https://www.rwe.com/en/rwe-careers-portal/job-offers/details/?id=83330-en_GB"
        },
        {
          "title": "Corporate Counsel",
          "company": "Amazon",
          "link": "https://amazon.jobs/en/jobs/2459798/corporate-counsel"
        },
        {
          "title": "Counsel",
          "company": "Major League Baseball",
          "link": "https://www.mlb.com/careers/opportunities?gh_jid=5381931"
        },
        {
          "title": "Counsel, Corporate",
          "company": "Warner Music Group",
          "link": "https://wmg.wd1.myworkdayjobs.com/en-US/WMGUS/job/Counsel--Corporate_R-020938"
        },
        {
          "title": "Senior Counsel, Content",
          "company": "Condé Nast",
          "link": "https://condenast.wd5.myworkdayjobs.com/en-US/CondeCareers/job/Senior-Counsel--Content_R-14318-1"
        },
        {
          "title": "Senior Counsel, Employment Law",
          "company": "Paramount",
          "link": "https://careers.paramount.com/job/New-York-Senior-Counsel%2C-Employment-Law-NY-10020/1078811100/"
        },
        {
          "title": "Senior Counsel, Legal",
          "company": "New York City Economic Development Corporation",
          "link": "https://boards.greenhouse.io/nycedc/jobs/4270956006"
        },
        {
          "title": "Staff Attorney, Disability Advocacy Project",
          "company": "Manhattan Legal Services",
          "link": "https://www.legalservicesnyc.org/get-involved/opportunities/8-job-openings-and-internships/1998-staff-attorney-disability-advocacy-project-job-562023"
        }
      ]
    },
    {
      "area": "Texas - Austin Metro Area",
      "jobs": [
        {
          "title": "Administrative Law Judge",
          "company": "Texas Department of Insurance",
          "link": "https://capps.taleo.net/careersection/ex/jobdetail.ftl?job=00037201"
        },
        {
          "title": "Assistant City Attorney I or II",
          "company": "City of Austin",
          "link": "https://www.austincityjobs.org/postings/112760"
        },
        {
          "title": "Corporate Attorney",
          "company": "RWE Clean Energy",
          "link": "https://www.rwe.com/en/rwe-careers-portal/job-offers/details/?id=83330-en_GB"
        },
        {
          "title": "Community Legal Services County Executive",
          "company": "Travis County",
          "link": "https://www.governmentjobs.com/careers/traviscounty/jobs/4199223/community-legal-services-county-executive"
        },
        {
          "title": "Employment and Ethics Attorney",
          "company": "Texas Commission on Environmental Quality",
          "link": "https://capps.taleo.net/careersection/582/jobdetail.ftl?job=00036754"
        },
        {
          "title": "Sr. Counsel, Commercial",
          "company": "Tesla",
          "link": "https://www.tesla.com/careers/search/job/sr-counsel-commercial-210302"
        }
      ]
    },
    {
      "area": "Washington - Seattle Metro Area",
      "jobs": [
        {
          "title": "Associate Legal Counsel",
          "company": "Blue Origin",
          "link": "https://blueorigin.wd5.myworkdayjobs.com/en-US/BlueOrigin/job/Associate-Legal-Counsel_R36922"
        },
        {
          "title": "Corporate Counsel",
          "company": "Amazon",
          "link": "https://amazon.jobs/en/jobs/2459798/corporate-counsel"
        },
        {
          "title": "Deputy General Counsel",
          "company": "Seattle Housing Authority",
          "link": "https://www.governmentjobs.com/careers/seattlehousing/jobs/4195945/deputy-general-counsel-i"
        },
        {
          "title": "Legal Counsel",
          "company": "Microsoft",
          "link": "https://jobs.careers.microsoft.com/global/en/job/1605547/Legal-Counsel"
        },
        {
          "title": "Legal Counsel - Seattle",
          "company": "Lululemon",
          "link": "https://careers.lululemon.com/en_US/careers/JobDetail/Legal-Counsel-Seattle/29518"
        },
        {
          "title": "Sr. Manager, Sr. Corporate Counsel (Product Safety)",
          "company": "The Pokémon Company International ",
          "link": "https://boards.greenhouse.io/pokemoncareers/jobs/5603056003"
        }
      ]
    }
  ]
}
