{
  "places": [
    {
      "area": "New York City or Washington, DC",
      "jobs": [
        {
          "title": "Bernard and Anne Spitzer Fellow (Mid-Level / Senior Attorney)",
          "company": "Brennan Center for Justice at NYU School of Law",
          "link": "https://brennancenter.applytojob.com/apply/NF3FmBKJU9/Bernard-And-Anne-Spitzer-Fellow"
        }
      ]
    },
    {
      "area": "Scottsdale / Phoenix, AZ; Jacksonville, FL; Rochester, MN; or Eau Claire, WI",
      "jobs": [
        {
          "title": "Attorney / Legal Counsel",
          "company": "Mayo Clinic",
          "link": "https://jobs.mayoclinic.org/jobs/attorney-legal-counsel-127163br"
        }
      ]
    },
    {
      "area": "Chicago or Washington, DC",
      "jobs": [
        {
          "title": "Associate General Counsel - Policy",
          "company": "Blue Cross Blue Shield Association",
          "link": "https://careers-bcbsa.icims.com/jobs/3303/associate-general-counsel---privacy/job"
        }
      ]
    },
    {
      "area": "California - Oakland or Los Angeles",
      "jobs": [
        {
          "title": "Litigation Attorney",
          "company": "Justice in Aging",
          "link": "https://www.justiceinaging.org/litigation-attorney/"
        }
      ]
    },
    {
      "area": "California - Los Angeles Metro Area",
      "jobs": [
        {
          "title": "Assistant General Counsel",
          "company": "CBS Television Studios",
          "link": "https://viacomcbs.careers/studio-city-ca/assistant-general-counsel/E1F9CEFF8FC6413CAD008D5344C3F347/job/"
        },
        {
          "title": "Assistant General Counsel",
          "company": "LA 2028",
          "link": "https://www.linkedin.com/jobs/view/1668411332"
        },
        {
          "title": "Corporate Counsel",
          "company": "SpaceX",
          "link": "https://boards.greenhouse.io/spacex/jobs/4588283002?gh_jid=4588283002"
        },
        {
          "title": "Director, Legal and Business Affairs",
          "company": "IMAX",
          "link": "https://imax-openhire.silkroad.com/epostings/index.cfm?fuseaction=app.jobinfo&jobid=1599"
        },
        {
          "title": "Sr. Counsel, Intellectual Property",
          "company": "NBCUniversal",
          "link": "https://sjobs.brassring.com/TGnewUI/Search/home/HomeWithPreLoad?PageType=JobDetails&partnerid=25354&siteid=5108&jobid=477899"
        }
      ]
    },
    {
      "area": "California - San Francisco Bay Area",
      "jobs": [
        {
          "title": "Associate Counsel",
          "company": "IDEO",
          "link": "https://www.ideo.com/jobs/legal/san-francisco/1992979/associate-counsel"
        },
        {
          "title": "Corporate Counsel",
          "company": "Revolution Foods",
          "link": "https://jobs.jobvite.com/revolutionfoods/job/oLjSbfwR"
        },
        {
          "title": "Corporate Counsel, Supercharger & Real Estate, Legal",
          "company": "Tesla",
          "link": "https://www.tesla.com/careers/job/corporate-counselsuperchargerrealestatelegal-56819"
        },
        {
          "title": "General Counsel",
          "company": "Plaid",
          "link": "https://plaid.com/job/?id=60af77d0-be0c-4436-a463-05583b0cd4e1"
        },
        {
          "title": "Investments Attorney",
          "company": "Chan Zuckerberg Initiative",
          "link": "https://boards.greenhouse.io/chanzuckerberginitiative/jobs/2011213?gh_jid=2011213"
        },
        {
          "title": "Litigation Program Staff Attorney",
          "company": "Animal Legal Defense Fund",
          "link": "https://aldf.org/article/employment-opportunities/entry/12179/"
        },
        {
          "title": "Senior Corporate Counsel",
          "company": "Impossible Foods",
          "link": "https://impossiblefoods.com/job-details/?id=6e9f8ec2-d2d1-474f-ac8d-acec43e3a6a7&team=Legal&title=Senior%20Corporate%20Counsel"
        },
        {
          "title": "Staff Attorney",
          "company": "Homeless Action Center",
          "link": "http://homelessactioncenter.org/get-involved/job-opportunities/"
        }
      ]
    },
    {
      "area": "California - Sacramento",
      "jobs": [
        {
          "title": "Attorney",
          "company": "Judicial Council of California",
          "link": "https://careers.jud.ca.gov/psp/recruit1/EMPLOYEE/HRMS/c/HRS_HRAM_FL.HRS_CG_SEARCH_FL.GBL?Page=HRS_APP_JBPST_FL&Action=U&FOCUS=Applicant&SiteId=1&JobOpeningId=5127&PostingSeq=2"
        },
        {
          "title": "Deputy Legislative Counsel",
          "company": "CA Office of Legislative Counsel",
          "link": "https://jobs.ca.gov/CalHrPublic/Jobs/JobPosting.aspx?JobControlId=187271"
        }
      ]
    },
    {
      "area": "Colorado - Denver Metro Area",
      "jobs": [
        {
          "title": "Associate General Counsel",
          "company": "Cochlear",
          "link": "http://careers.cochlear.com/cw/en/job/610474/associate-general-counsel"
        },
        {
          "title": "Sr. Commercial Counsel",
          "company": "Slack",
          "link": "https://slack.com/careers/2000527/sr-commercial-counsel"
        },
        {
          "title": "Senior Counsel, Ethics & Compliance (Americas & EMEA)",
          "company": "VF Corporation",
          "link": "https://vfc.wd5.myworkdayjobs.com/en-US/vfc_careers/job/USCA--USA--Colorado--Denver---WHQ/Director--Ethics---Compliance--Americas---EMEA-_R-20190226-0054-1"
        }
      ]
    },
    {
      "area": "DC - Washington Metro Area",
      "jobs": [
        {
          "title": "Assistant City Attorney",
          "company": "City of Alexandria",
          "link": "https://www.governmentjobs.com/careers/alexandria/jobs/2681026/assistant-city-attorney-i"
        },
        {
          "title": "Assistant Director and Senior Specialist (American Law Division)",
          "company": "Congressional Research Service",
          "link": "https://www.usajobs.gov/GetJob/ViewDetails/556274200"
        },
        {
          "title": "Attorney-Adviser (2 Positions)",
          "company": "Securities and Exchange Commission",
          "link": "https://www.usajobs.gov/GetJob/ViewDetails/556322500"
        },
        {
          "title": "Director, Law Firm Pro Bono Project",
          "company": "Pro Bono Institute",
          "link": "http://www.probonoinst.org/wpps/wp-content/uploads/PBI-Director-2019.pdf"
        },
        {
          "title": "Legal Fellow - Transparency in Government",
          "company": "NPR",
          "link": "https://recruiting.ultipro.com/NAT1011NATPR/JobBoard/af823b19-a43b-4cda-b6c2-c06508d84cf6/OpportunityDetail?opportunityId=6ad3ad2f-9da6-4985-aa65-1f39a61ec047"
        },
        {
          "title": "Program Director, Institute for Technology Law & Policy",
          "company": "Georgetown University Law Center",
          "link": "https://georgetown.wd1.myworkdayjobs.com/en-US/Georgetown_Admin_Careers/job/Law-Center/Program-Director--Institute-for-Technology-Law---Policy---Georgetown-University-Law-Center_JR08310"
        },
        {
          "title": "Staff Attorney",
          "company": "District of Columbia Court of Appeals",
          "link": "https://www.usajobs.gov/GetJob/ViewDetails/556325900"
        }
      ]
    },
    {
      "area": "Illinois - Chicago Metro Area",
      "jobs": [
        {
          "title": "Associate General Counsel",
          "company": "Dyson",
          "link": "https://careers.dyson.com/en-gb/job-description/associate-general-counsel/30881"
        },
        {
          "title": "Corporate Counsel",
          "company": "Ace Hardware Corporation",
          "link": "https://acehardware.wd1.myworkdayjobs.com/en-US/External/job/IL---Oak-Brook/Corporate-Counsel_REQ-05344"
        },
        {
          "title": "Managing Attorney – Diversity & Professionalism Programs",
          "company": "Illinois Supreme Court Commission on Professionalism",
          "link": "https://www.2civility.org/about/careers/"
        }
      ]
    },
    {
      "area": "Massachusetts - Boston Metro Area",
      "jobs": [
        {
          "title": "Associate General Counsel",
          "company": "ASICS America Corporation",
          "link": "https://career5.successfactors.eu/career?company=S003910448P&site=VjItR2U0ZmpQVjVzUDcwUnBWUG54ZmgyZz09&career_job_req_id=37319&career_ns=job_listing&navBarLevel=JOB_SEARCH"
        },
        {
          "title": "Clinical Instructor (Harvard Negotiation and Mediation Clinic)",
          "company": "Harvard Law School",
          "link": "https://sjobs.brassring.com/TGnewUI/Search/Home/HomeWithPreLoad?partnerid=25240&siteid=5341&PageType=searchResults&SearchType=linkquery&LinkID=1233#jobDetails=1505383_5341"
        },
        {
          "title": "Counsel",
          "company": "Samsonite",
          "link": "https://careers-samsonite.icims.com/jobs/3110/counsel/job"
        },
        {
          "title": "Legal Fellow (Legal Assistance to Victims Project)",
          "company": "Northeastern University School of Law",
          "link": "https://careers.hrm.northeastern.edu/en-us/job/502464/legal-fellow"
        },
        {
          "title": "Staff Attorney, Mental Health Legal Advisors Committee",
          "company": "Massachusetts Supreme Judicial Court",
          "link": "https://massanf.taleo.net/careersection/ex/jobdetail.ftl?job=190009UY&tz=GMT-06:00&tzname=America/Chicago&src=JB-10080"
        }
      ]
    },
    {
      "area": "New York - New York City",
      "jobs": [
        {
          "title": "Assistant Corporation Counsel (Tax & Bankruptcy)",
          "company": "New York City Law Department",
          "link": "https://a127-jobs.nyc.gov/psc/nycjobs/EMPLOYEE/HRMS/c/HRS_HRAM.HRS_APP_SCHJOB.GBL?Page=HRS_APP_JBPST&Action=U&FOCUS=Applicant&SiteId=1&JobOpeningId=427351&PostingSeq=1"
        },
        {
          "title": "Assistant General Counsel (part-time)",
          "company": "Brooklyn Museum",
          "link": "https://www.brooklynmuseum.org/about/careers/assistant_general_counsel"
        },
        {
          "title": "Assistant General Counsel",
          "company": "NYC Department of Veterans' Services",
          "link": "https://a127-jobs.nyc.gov/psc/nycjobs/EMPLOYEE/HRMS/c/HRS_HRAM.HRS_APP_SCHJOB.GBL?Page=HRS_APP_JBPST&Action=U&FOCUS=Applicant&SiteId=1&JobOpeningId=426601&PostingSeq=1"
        },
        {
          "title": "Counsel",
          "company": "Major League Baseball",
          "link": "https://www.mlb.com/careers/opportunities?gh_jid=2000971"
        },
        {
          "title": "General Counsel",
          "company": "Kickstarter",
          "link": "https://www.kickstarter.com/jobs/general-counsel-fe160cc4"
        },
        {
          "title": "General Counsel",
          "company": "Urban Resource Institute",
          "link": "https://urinyc.org/career/general-counsel/"
        },
        {
          "title": "VP of Legal",
          "company": "Industrious",
          "link": "https://boards.greenhouse.io/industrious/jobs/2025577"
        }
      ]
    },
    {
      "area": "Texas - Austin Metro Area",
      "jobs": [
        {
          "title": "Assistant City Attorney",
          "company": "City of Austin",
          "link": "https://www.austincityjobs.org/postings/81613"
        },
        {
          "title": "Legislative Counsel",
          "company": "Texas Legislative Council",
          "link": "https://tlc.texas.gov/docs/postings/20006%20Legislative%20Counsel%20I.pdf"
        }
      ]
    },
    {
      "area": "Washington - Seattle Metro Area",
      "jobs": [
        {
          "title": "Associate Attorney, Northwest",
          "company": "Earthjustice",
          "link": "https://earthjustice.org/about/jobs/38594/associate-attorney-northwest"
        },
        {
          "title": "Club Counsel",
          "company": "Seattle Sounders FC",
          "link": "https://www.teamworkonline.com/soccer-jobs/mls/seattle-sounders/club-counsel-1969706"
        },
        {
          "title": "Corporate Counsel",
          "company": "Zillow Group",
          "link": "https://careers.zillowgroup.com/ShowJob/JobId/386801/CorporateCounsel"
        }
      ]
    }
  ]
}
