{
  "clients": {
    "title": "[title]",
    "link": "#",
    "description": [
      "Lorem ipsum dolor sit amet, consectetur adipisicing elit. Necessitatibus expedita, ipsam sapiente distinctio at vero aliquam enim quaerat dolore reiciendis maiores porro tempora quibusdam.",
      "Esse libero laudantium id, sed cupiditate."
    ]
  },
  "jld": {
    "title": "[title]",
    "link": "#",
    "description": [
      "Lorem ipsum dolor sit amet, consectetur adipisicing elit. Error harum perspiciatis vel, cupiditate recusandae odio, repellat sint!",
      "Doloribus debitis corporis illo culpa officiis qui, tempore harum suscipit id possimus maiores!"
    ]
  }
}
